AUTHORS.rst
CONTRIBUTING.rst
HISTORY.rst
LICENSE
MANIFEST.in
README.rst
setup.cfg
setup.py
djangocms_responsive_wrapper.egg-info/PKG-INFO
djangocms_responsive_wrapper.egg-info/SOURCES.txt
djangocms_responsive_wrapper.egg-info/dependency_links.txt
djangocms_responsive_wrapper.egg-info/not-zip-safe
djangocms_responsive_wrapper.egg-info/pbr.json
djangocms_responsive_wrapper.egg-info/requires.txt
djangocms_responsive_wrapper.egg-info/top_level.txt
responsive_wrapper/__init__.py
responsive_wrapper/cms_app.py
responsive_wrapper/cms_plugins.py
responsive_wrapper/conf.py
responsive_wrapper/fields.py
responsive_wrapper/forms.py
responsive_wrapper/models.py
responsive_wrapper/urls.py
responsive_wrapper/utils.py
responsive_wrapper/views.py
responsive_wrapper/migrations/0001_initial.py
responsive_wrapper/migrations/__init__.py
responsive_wrapper/south_migrations/0001_initial.py
responsive_wrapper/south_migrations/__init__.py
responsive_wrapper/static/js/responsive_wrapper/jquery.responsive-wrapper.js
responsive_wrapper/templates/responsive_wrapper/default.html
responsive_wrapper/templates/responsive_wrapper/live_reload.html
responsive_wrapper/templates/responsive_wrapper/render_plugin.html