Metadata-Version: 1.1
Name: djangocms-responsive-wrapper
Version: 0.2.1
Summary: This projects integrates django-responsive2 with django-cms >= 3.0
Home-page: https://github.com/mishbahr/djangocms-responsive-wrapper
Author: Mishbah Razzaque
Author-email: mishbahx@gmail.com
License: BSD
Keywords: djangocms-responsive-wrapper,django-responsive2,django-cms
Platform: UNKNOWN
Classifier: Development Status :: 4 - Beta
Classifier: Framework :: Django
Classifier: Intended Audience :: Developers
Classifier: License :: OSI Approved :: BSD License
Classifier: Natural Language :: English
Classifier: Programming Language :: Python :: 2.7
Classifier: Programming Language :: Python :: 3
Classifier: Programming Language :: Python :: 3.3
